src/__init__.py
src/main.py
fusionx3-0.0.1.dist-info/METADATA
fusionx3-0.0.1.dist-info/WHEEL
fusionx3-0.0.1.dist-info/top_level.txt
fusionx3-0.0.1.dist-info/RECORD
