Metadata-Version: 2.1
Name: fusionx3
Version: 0.0.1
Summary: fusionx3
Author: FusionX (a)
Author-email: <bar.bendavid@weiamann.ac.il>
Keywords: python,video,stream,video stream,camera stream,sockets
Classifier: Development Status :: 1 - Planning
Classifier: Intended Audience :: Developers
Classifier: Programming Language :: Python :: 3
Classifier: Operating System :: Unix
Classifier: Operating System :: MacOS :: MacOS X
Classifier: Operating System :: Microsoft :: Windows
